Bububugti/Bububugti.py
Bububugti/__init__.py
ModBububugti-1.0.0.dist-info/METADATA
ModBububugti-1.0.0.dist-info/WHEEL
ModBububugti-1.0.0.dist-info/top_level.txt
ModBububugti-1.0.0.dist-info/RECORD
