Metadata-Version: 2.1
Name: ModBububugti
Version: 1.0.0
Summary: Una biblioteca para mostrar mensajes de error y sus imágenes correspondientes.
Home-page: https://github.com/SpectralMoon7w7/ModBububugti
Author: Juan Carlos Hurtado
Author-email: j.c.hurtado.t.businessm@gmail.com
Classifier: License :: OSI Approved :: MIT License
Classifier: Programming Language :: Python :: 3
Classifier: Programming Language :: Python :: 3.8
Classifier: Programming Language :: Python :: 3.9
Classifier: Programming Language :: Python :: 3.10
